MANIFEST.in
README.md
setup.cfg
setup.py
specdist/__init__.py
specdist/config.py
specdist/cosmology.py
specdist/cosmotherm_wrapper.py
specdist/edges_data.py
specdist/firas_data.py
specdist/interpolate_ct_spectra.py
specdist/pispec_functions.py
specdist/specdist_functions.py
specdist/standard_mu_and_y_distortions.py
specdist/utils.py
specdist.egg-info/PKG-INFO
specdist.egg-info/SOURCES.txt
specdist.egg-info/dependency_links.txt
specdist.egg-info/not-zip-safe
specdist.egg-info/top_level.txt
specdist/data/firas_monopole_spec_v1.txt