Metadata-Version: 1.1
Name: specdist
Version: 0.0
Summary: Python package for spectral distortions
Home-page: https://github.com/borisbolliet/specdist
Author: Boris Bolliet and Jens Chluba
Author-email: boris.bolliet@gmail.com
License: UNKNOWN
Download-URL: https://github.com/borisbolliet/specdist/archive/master.zip
Platform: UNKNOWN
